MANIFEST.in
README.md
compatible_packages.json
pyproject.toml
setup.py
mr_creosote/__init__.py
mr_creosote.egg-info/PKG-INFO
mr_creosote.egg-info/SOURCES.txt
mr_creosote.egg-info/dependency_links.txt
mr_creosote.egg-info/entry_points.txt
mr_creosote.egg-info/not-zip-safe
mr_creosote.egg-info/requires.txt
mr_creosote.egg-info/top_level.txt