Metadata-Version: 2.4
Name: mr-creosote
Version: 1.0.0
Summary: I'll have the lot.
Requires-Python: >=3.10
Requires-Dist: techdragon
Dynamic: requires-dist
Dynamic: requires-python
